elenchos/__init__.py
elenchos/application/ElenchosApplication.py
elenchos/application/ElenchosCommandLoader.py
elenchos/application/__init__.py
elenchos/command/CheckCommand.py
elenchos/command/GatherCommandsCommand.py
elenchos/command/__init__.py
elenchos/helper/XmlHelper.py
elenchos/helper/__init__.py
elenchos/io/ElenchosIO.py
elenchos/io/__init__.py
elenchos/nagios/IncludeInDescription.py
elenchos/nagios/NagiosPlugin.py
elenchos/nagios/NagiosStatus.py
elenchos/nagios/PerformanceData.py
elenchos/nagios/__init__.py
elenchos-1.2.0.dist-info/LICENSE.md
elenchos-1.2.0.dist-info/METADATA
elenchos-1.2.0.dist-info/WHEEL
elenchos-1.2.0.dist-info/entry_points.txt
elenchos-1.2.0.dist-info/RECORD
